gist_search/__init__.py
gist_search/search.py
gist_search/utils.py
search_gists-0.1.dist-info/DESCRIPTION.rst
search_gists-0.1.dist-info/METADATA
search_gists-0.1.dist-info/RECORD
search_gists-0.1.dist-info/WHEEL
search_gists-0.1.dist-info/entry_points.txt
search_gists-0.1.dist-info/metadata.json
search_gists-0.1.dist-info/top_level.txt
