Metadata-Version: 2.0
Name: search-gists
Version: 0.1
Summary: Search pubic gists for user
Home-page: https://rmotr.com
Author: Santiago Basulto
Author-email: santiago.basulto@gmail.com
License: UNKNOWN
Platform: UNKNOWN
Requires-Dist: click (==6.7)
Requires-Dist: requests (==2.18.4)
Provides-Extra: dev
Requires-Dist: pytest (==3.4.1); extra == 'dev'
Requires-Dist: responses (==0.8.1); extra == 'dev'
